V3SProtoComm/__init__.py
V3SProtoComm/core/__init__.py
V3SProtoComm/core/command.py
V3SProtoComm/core/data.py
V3SProtoComm/core/comm/__init__.py
V3SProtoComm/core/comm/controls.py
V3SProtoComm/core/comm/receiver.py
V3SProtoComm/core/comm/referee.py
V3SProtoComm/core/comm/replacer.py
V3SProtoComm/core/comm/thread_job.py
V3SProtoComm/core/comm/transmitter.py
V3SProtoComm/core/comm/vision.py
V3SProtoComm/core/comm/protocols/__init__.py
V3SProtoComm/core/comm/protocols/command_pb2.py
V3SProtoComm/core/comm/protocols/common_pb2.py
V3SProtoComm/core/comm/protocols/messages_robocup_ssl_detection_pb2.py
V3SProtoComm/core/comm/protocols/messages_robocup_ssl_geometry_pb2.py
V3SProtoComm/core/comm/protocols/packet_pb2.py
V3SProtoComm/core/comm/protocols/replacement_pb2.py
V3SProtoComm/core/comm/protocols/vssref_command_pb2.py
V3SProtoComm/core/comm/protocols/vssref_common_pb2.py
V3SProtoComm/core/comm/protocols/vssref_placement_pb2.py
V3SProtoComm/core/comm/protocols/wrapper_pb2.py
V3SProtoComm/core/comm/protocols/protobuf/__init__.py
v3sprotocomm-2.1.0.dist-info/METADATA
v3sprotocomm-2.1.0.dist-info/WHEEL
v3sprotocomm-2.1.0.dist-info/entry_points.txt
v3sprotocomm-2.1.0.dist-info/top_level.txt
v3sprotocomm-2.1.0.dist-info/RECORD
