Metadata-Version: 2.4
Name: V3SProtoComm
Version: 2.1.0
Summary: Pacote para comunicação e controle de robôs via Protobuf
Home-page: https://github.com/Taurabots/V3SProtoComm
Author: Thassio
Author-email: thxssio@gmail.com
Requires-Dist: numpy
Requires-Dist: protobuf
Requires-Dist: six
Requires-Dist: toml
Requires-Dist: wrapt
Dynamic: author
Dynamic: author-email
Dynamic: description
Dynamic: description-content-type
Dynamic: home-page
Dynamic: requires-dist
Dynamic: summary
